{
    "yellow": [
        "10YR 7-6",
        "10YR 7-8",
        "10YR 8-6",
        "10YR 8-8",
        "2.5Y 7-6",
        "2.5Y 7-8",
        "2.5Y 8-6",
        "2.5Y 8-8",
        "5Y 7-6",
        "5Y 7-8",
        "5Y 8-6",
        "5Y 8-8"
    ],
    "brownish_yellow": [
        "10YR 6-6",
        "10YR 6-8"
    ],
    "pale_yellow": [
        "5Y 7-4",
        "5Y 8-2",
        "5Y 8-4"
    ],
    "reddish_yellow": [
        "5YR 6-6",
        "5YR 6-8",
        "5YR 7-6",
        "5YR 7-8",
        "7.5YR 6-6",
        "7.5YR 6-8",
        "7.5YR 7-6",
        "7.5YR 7-8"
    ],
    "olive_yellow": [
        "2.5Y 6-6",
        "2.5Y 6-8",
        "5Y 6-6",
        "5Y 6-8"
    ],
    "white": [
        "N 10-0"
    ],
    "pinkish_white": [
        "10R 8-2",
        "2.5YR 8-2",
        "5YR 8-2",
        "7.5YR 8-2"
    ],
    "red": [
        "10R 4-6",
        "10R 4-8",
        "10R 5-6",
        "10R 5-8",
        "2.5YR 4-6",
        "2.5YR 4-8",
        "2.5YR 5-6",
        "2.5YR 5-8",
        "5R 4-6",
        "5R 4-8",
        "5R 5-6",
        "5R 5-8",
        "7.5R 4-6",
        "7.5R 4-8",
        "7.5R 5-6",
        "7.5R 5-8"
    ],
    "yellowish_red": [
        "5YR 4-6",
        "5YR 5-6",
        "5YR 5-8"
    ],
    "very_dusky_red": [
        "5R 2-2",
        "5R 2-4",
        "10R 2-2",
        "2.5YR 2-2",
        "7.5R 2-2",
        "7.5R 2-4"
    ],
    "dusky_red": [
        "10R 3-2",
        "10R 3-4",
        "2.5YR 3-2",
        "5R 3-2",
        "5R 3-4",
        "7.5R 3-2",
        "7.5R 3-4"
    ],
    "light_red": [
        "10R 6-6",
        "10R 6-8",
        "10R 7-6",
        "10R 7-8",
        "2.5YR 6-6",
        "2.5YR 6-8",
        "2.5YR 7-6",
        "2.5YR 7-8",
        "5R 6-6",
        "5R 6-8",
        "5R 7-6",
        "5R 7-8",
        "7.5R 6-6",
        "7.5R 6-8",
        "7.5R 7-6",
        "7.5R 7-8"
    ],
    "dark_red": [
        "10R 3-6",
        "2.5YR 3-6",
        "2.5YR 3-8",
        "5R 2-6",
        "5R 3-6",
        "5R 3-8",
        "7.5R 3-6",
        "7.5R 3-8"
    ],
    "pale_red": [
        "10R 6-2",
        "10R 6-4",
        "10R 7-2",
        "10R 7-4",
        "2.5YR 6-2",
        "2.5YR 7-2",
        "5R 6-2",
        "5R 6-4",
        "5R 7-2",
        "5R 7-4",
        "7.5R 6-2",
        "7.5R 6-4",
        "7.5R 7-2",
        "7.5R 7-4"
    ],
    "weak_red": [
        "10R 4-2",
        "10R 4-4",
        "10R 5-2",
        "10R 5-4",
        "2.5YR 4-2",
        "2.5YR 5-2",
        "5R 4-2",
        "5R 4-4",
        "5R 5-2",
        "5R 5-4",
        "7.5R 4-2",
        "7.5R 4-4",
        "7.5R 5-2",
        "7.5R 5-4"
    ],
    "pink": [
        "10R 8-4",
        "2.5YR 8-4",
        "5YR 7-4",
        "5YR 8-4",
        "7.5YR 7-4",
        "7.5YR 8-4"
    ],
    "light_pink": [
        "5R 8-2",
        "5R 8-4",
        "7.5R 8-2",
        "7.5R 8-4"
    ],
    "olive": [
        "5Y 4-4",
        "5Y 5-4",
        "5Y 5-6"
    ],
    "pale_olive": [
        "5Y 6-4"
    ],
    "gray": [
        "10YR 6-1",
        "2.5Y 6-1",
        "5Y 6-1",
        "5YR 6-1",
        "7.5YR 6-1"
    ],
    "dark_gray": [
        "2.5Y 4-1",
        "5YR 4-1"
    ],
    "reddish_gray": [
        "10R 6-1",
        "2.5YR 6-1",
        "5R 6-1",
        "5YR 5-2",
        "7.5R 6-1"
    ],
    "dark_reddish_gray": [
        "10R 4-1",
        "2.5YR 4-1",
        "5R 4-1",
        "5YR 4-2",
        "7.5R 4-1"
    ],
    "light_brownish_gray": [
        "10YR 6-2",
        "2.5Y 6-2"
    ],
    "light_gray": [
        "10YR 7-1",
        "10YR 7-2",
        "2.5Y 7-2",
        "5Y 7-2",
        "7.5YR 7-1"
    ],
    "light_olive_gray": [
        "5Y 6-2"
    ],
    "dark_olive_gray": [
        "5Y 3-2"
    ],
    "light_reddish_gray": [],
    "pinkish_gray": [
        "5YR 6-2",
        "5YR 7-2",
        "7.5YR 6-2",
        "7.5YR 7-2"
    ],
    "very_dark_gray": [
        "2.5Y 3-1",
        "5YR 3-1"
    ],
    "olive_gray": [
        "5Y 4-2",
        "5Y 5-2"
    ],
    "brown": [
        "10YR 5-3",
        "7.5YR 4-2",
        "7.5YR 4-4",
        "7.5YR 5-2",
        "7.5YR 5-4"
    ],
    "dark_brown": [
        "7.5YR 3-2",
        "7.5YR 3-4"
    ],
    "dark_grayish_brown": [
        "10YR 4-2",
        "2.5Y 4-2"
    ],
    "reddish_brown": [
        "2.5YR 4-4",
        "2.5YR 5-4",
        "5YR 4-4",
        "5YR 5-4"
    ],
    "dark_reddish_brown": [
        "2.5YR 2-4",
        "2.5YR 3-4",
        "5YR 2-2",
        "5YR 3-2",
        "5YR 3-4"
    ],
    "dark_yellowish_brown": [
        "10YR 3-4",
        "10YR 3-6",
        "10YR 4-4",
        "10YR 4-6"
    ],
    "grayish_brown": [
        "10YR 5-2",
        "2.5Y 5-2"
    ],
    "light_brown": [
        "7.5YR 6-4"
    ],
    "light_olive_brown": [
        "2.5Y 5-4",
        "2.5Y 5-6"
    ],
    "dark_olive_brown": [],
    "light_reddish_brown": [
        "2.5YR 6-4",
        "2.5YR 7-4",
        "5YR 6-4"
    ],
    "light_yellowish_brown": [
        "10YR 6-4",
        "2.5Y 6-4"
    ],
    "pale_brown": [
        "2.5Y 7-3",
        "2.5Y 7-4",
        "2.5Y 8-2",
        "2.5Y 8-4"
    ],
    "yellowish_brown": [
        "10YR 5-4",
        "10YR 5-6",
        "10YR 5-8"
    ],
    "strong_brown": [
        "7.5YR 4-6",
        "7.5YR 5-6",
        "7.5YR 5-8"
    ],
    "very_dark_brown": [
        "10YR 2-2",
        "7.5YR 2-2"
    ],
    "very_dark_grayish_brown": [
        "10YR 3-2",
        "2.5Y 3-2"
    ],
    "very_pale_brown": [
        "10YR 7-4",
        "10YR 8-2",
        "10YR 8-4"
    ],
    "olive_brown": [
        "2.5Y 4-4"
    ],
    "black": [
        "N 0-0"
    ],
    "reddish_black": [
        "2.5YR 2-1",
        "7.5R 2-1"
    ]
}